phy_rx/probador_RX.v
module probador_serial_paraleloRX (
			
			//entradas
			output reg data_in,			//entrada de datos a 32f
			output reg reset,			//
			output reg clk_32f,			//clock frecuencia 32
			output reg clk_4f,			//clock frecuencia 4
			output reg clk_2f,
			output reg clk_f,
	
			//Salidas
            input out_serial2_conductual,//salida de paralelo serial rx
            input out_serial2_conductual_s,//salida paralelo seria rx sint
            input [7:0]Salida0,//salida demux
            input [7:0]Salida1,//salida demux
            input [7:0]Salida2,//salida demux
            input [7:0]Salida3,//salida demux
            input validSalida0,
            input validSalida1,
            input validSalida2,
            input validSalida3,
            input [7:0]Salida0s,//salida demux sint
            input [7:0]Salida1s,//salida demux sint
            input [7:0]Salida2s,//salida demux sint
            input [7:0]Salida3s,//salida demux sint
            input validSalida0s,
            input validSalida1s,
            input validSalida2s,
            input validSalida3s
);

	initial begin
	$dumpfile("RX.vcd");
	$dumpvars;
	@(posedge clk_2f);


	@(posedge clk_4f);
	reset <= 0;
	data_in<=1;
	@(posedge clk_32f)
	data_in<=0;
	@(posedge clk_32f)
	data_in<=1;
	@(posedge clk_32f)
	data_in<=1;
	@(posedge clk_32f)
	data_in<=1;
	@(posedge clk_32f)
	data_in<=1;
	@(posedge clk_32f)
	data_in<=0;
	@(posedge clk_32f)
	data_in<=0;


	@(posedge clk_4f);
	data_in<=0;
	@(posedge clk_32f)
	data_in<=0;
	@(posedge clk_32f)
	data_in<=1;
	@(posedge clk_32f)
	data_in<=1;
	@(posedge clk_32f)
	data_in<=1;
	@(posedge clk_32f)
	data_in<=1;
	@(posedge clk_32f)
	data_in<=0;
	@(posedge clk_32f)
	data_in<=0;

	@(posedge clk_2f);

	@(posedge clk_4f);
	reset <=1;
	data_in<=1;
	@(posedge clk_32f)
	data_in<=0;
	@(posedge clk_32f)
	data_in<=1;
	@(posedge clk_32f)
	data_in<=1;
	@(posedge clk_32f)
	data_in<=1;
	@(posedge clk_32f)
	data_in<=1;
	@(posedge clk_32f)
	data_in<=0;
	@(posedge clk_32f)
	data_in<=1;

	@(posedge clk_4f);
	data_in<=1;
	reset <=1;
	@(posedge clk_32f)
	data_in<=1;
	@(posedge clk_32f)
	data_in<=1;
	@(posedge clk_32f)
	data_in<=1;
	@(posedge clk_32f)
	data_in<=0;
	@(posedge clk_32f)
	data_in<=1;
	@(posedge clk_32f)
	data_in<=0;
	@(posedge clk_32f)
	data_in<=0;


	@(posedge clk_2f);

	@(posedge clk_4f);
	data_in<=1;
	@(posedge clk_32f)
	data_in<=0;
	@(posedge clk_32f)
	data_in<=1;
	@(posedge clk_32f)
	data_in<=1;
	@(posedge clk_32f)
	data_in<=1;
	@(posedge clk_32f)
	data_in<=1;
	@(posedge clk_32f)
	data_in<=0;
	@(posedge clk_32f)
	data_in<=0;

	@(posedge clk_4f);
	data_in<=1;
	@(posedge clk_32f)
	data_in<=0;
	@(posedge clk_32f)
	data_in<=1;
	@(posedge clk_32f)
	data_in<=1;
	@(posedge clk_32f)
	data_in<=1;
	@(posedge clk_32f)
	data_in<=1;
	@(posedge clk_32f)
	data_in<=0;
	@(posedge clk_32f)
	data_in<=0;

	@(posedge clk_4f);
	data_in<=1;
	@(posedge clk_32f)
	data_in<=0;
	@(posedge clk_32f)
	data_in<=1;
	@(posedge clk_32f)
	data_in<=1;
	@(posedge clk_32f)
	data_in<=1;
	@(posedge clk_32f)
	data_in<=1;
	@(posedge clk_32f)
	data_in<=0;
	@(posedge clk_32f)
	data_in<=0;

	@(posedge clk_4f);
	data_in<=1;
	@(posedge clk_32f)
	data_in<=0;
	@(posedge clk_32f)
	data_in<=1;
	@(posedge clk_32f)
	data_in<=1;
	@(posedge clk_32f)
	data_in<=1;
	@(posedge clk_32f)
	data_in<=1;
	@(posedge clk_32f)
	data_in<=0;
	@(posedge clk_32f)
	data_in<=0;


	@(posedge clk_4f);
	data_in<=1;
	@(posedge clk_32f)
	data_in<=1;
	@(posedge clk_32f)
	data_in<=1;
	@(posedge clk_32f)
	data_in<=1;
	@(posedge clk_32f)
	data_in<=1;
	@(posedge clk_32f)
	data_in<=1;
	@(posedge clk_32f)
	data_in<=0;
	@(posedge clk_32f)
	data_in<=0;


	@(posedge clk_4f);
	data_in<=1;
	@(posedge clk_32f)
	data_in<=0;
	@(posedge clk_32f)
	data_in<=1;
	@(posedge clk_32f)
	data_in<=1;
	@(posedge clk_32f)
	data_in<=1;
	@(posedge clk_32f)
	data_in<=0;
	@(posedge clk_32f)
	data_in<=0;
	@(posedge clk_32f)
	data_in<=0;

	
@(posedge clk_4f);
	data_in<=1;
	@(posedge clk_32f)
	data_in<=0;
	@(posedge clk_32f)
	data_in<=1;
	@(posedge clk_32f)
	data_in<=1;
	@(posedge clk_32f)
	data_in<=1;
	@(posedge clk_32f)
	data_in<=0;
	@(posedge clk_32f)
	data_in<=0;
	@(posedge clk_32f)
	data_in<=0;


	@(posedge clk_4f);
	data_in<=1;
	@(posedge clk_32f)
	data_in<=0;
	@(posedge clk_32f)
	data_in<=1;
	@(posedge clk_32f)
	data_in<=1;
	@(posedge clk_32f)
	data_in<=1;
	@(posedge clk_32f)
	data_in<=1;
	@(posedge clk_32f)
	data_in<=0;
	@(posedge clk_32f)
	data_in<=0;

		
	
	@(posedge clk_4f);
	data_in<=1;
	@(posedge clk_32f)
	data_in<=0;
	@(posedge clk_32f)
	data_in<=1;
	@(posedge clk_32f)
	data_in<=1;
	@(posedge clk_32f)
	data_in<=1;
	@(posedge clk_32f)
	data_in<=1;
	@(posedge clk_32f)
	data_in<=0;
	@(posedge clk_32f)
	data_in<=0;


	@(posedge clk_4f);
	data_in<=1;
	@(posedge clk_32f)
	data_in<=1;
	@(posedge clk_32f)
	data_in<=1;
	@(posedge clk_32f)
	data_in<=1;
	@(posedge clk_32f)
	data_in<=1;
	@(posedge clk_32f)
	data_in<=1;
	@(posedge clk_32f)
	data_in<=0;
	@(posedge clk_32f)
	data_in<=0;


	@(posedge clk_4f);
	data_in<=0;
	@(posedge clk_32f)
	data_in<=0;
	@(posedge clk_32f)
	data_in<=1;
	@(posedge clk_32f)
	data_in<=0;
	@(posedge clk_32f)
	data_in<=0;
	@(posedge clk_32f)
	data_in<=1;
	@(posedge clk_32f)
	data_in<=0;
	@(posedge clk_32f)
	data_in<=1;

	@(posedge clk_4f);
	data_in<=0;
	@(posedge clk_32f)
	data_in<=0;
	@(posedge clk_32f)
	data_in<=1;
	@(posedge clk_32f)
	data_in<=1;
	@(posedge clk_32f)
	data_in<=1;
	@(posedge clk_32f)
	data_in<=1;
	@(posedge clk_32f)
	data_in<=0;
	@(posedge clk_32f)
	data_in<=1;



	@(posedge clk_4f);
	data_in<=1;
	@(posedge clk_32f)
	data_in<=0;
	@(posedge clk_32f)
	data_in<=0;
	@(posedge clk_32f)
	data_in<=1;
	@(posedge clk_32f)
	data_in<=1;
	@(posedge clk_32f)
	data_in<=1;
	@(posedge clk_32f)
	data_in<=1;
	@(posedge clk_32f)
	data_in<=0;


	@(posedge clk_4f);
	data_in<=1;
	@(posedge clk_32f)
	data_in<=1;
	@(posedge clk_32f)
	data_in<=0;
	@(posedge clk_32f)
	data_in<=1;
	@(posedge clk_32f)
	data_in<=0;
	@(posedge clk_32f)
	data_in<=1;
	@(posedge clk_32f)
	data_in<=0;
	@(posedge clk_32f)
	data_in<=0;
	@(posedge clk_4f);
	reset <=1;
	data_in<=1;
	@(posedge clk_32f)
	data_in<=0;
	@(posedge clk_32f)
	data_in<=1;
	@(posedge clk_32f)
	data_in<=1;
	@(posedge clk_32f)
	data_in<=1;
	@(posedge clk_32f)
	data_in<=1;
	@(posedge clk_32f)
	data_in<=0;
	@(posedge clk_32f)
	data_in<=1;

	@(posedge clk_4f);
	data_in<=1;
	reset <=1;
	@(posedge clk_32f)
	data_in<=1;
	@(posedge clk_32f)
	data_in<=1;
	@(posedge clk_32f)
	data_in<=1;
	@(posedge clk_32f)
	data_in<=0;
	@(posedge clk_32f)
	data_in<=1;
	@(posedge clk_32f)
	data_in<=0;
	@(posedge clk_32f)
	data_in<=0;


	@(posedge clk_2f);

	@(posedge clk_4f);
	data_in<=1;
	@(posedge clk_32f)
	data_in<=0;
	@(posedge clk_32f)
	data_in<=1;
	@(posedge clk_32f)
	data_in<=1;
	@(posedge clk_32f)
	data_in<=1;
	@(posedge clk_32f)
	data_in<=1;
	@(posedge clk_32f)
	data_in<=0;
	@(posedge clk_32f)
	data_in<=0;

	@(posedge clk_4f);
	data_in<=1;
	@(posedge clk_32f)
	data_in<=0;
	@(posedge clk_32f)
	data_in<=1;
	@(posedge clk_32f)
	data_in<=1;
	@(posedge clk_32f)
	data_in<=1;
	@(posedge clk_32f)
	data_in<=1;
	@(posedge clk_32f)
	data_in<=0;
	@(posedge clk_32f)
	data_in<=0;

	@(posedge clk_4f);
	data_in<=1;
	@(posedge clk_32f)
	data_in<=0;
	@(posedge clk_32f)
	data_in<=1;
	@(posedge clk_32f)
	data_in<=1;
	@(posedge clk_32f)
	data_in<=1;
	@(posedge clk_32f)
	data_in<=1;
	@(posedge clk_32f)
	data_in<=0;
	@(posedge clk_32f)
	data_in<=0;




			
	$finish;
	end
	initial clk_f <= 0;
	always #32 clk_f <= ~clk_f;

	initial clk_2f <= 0;
	always #16 clk_2f <= ~clk_2f;


	initial clk_4f <= 1;
	always #8 clk_4f <= ~clk_4f;

	initial clk_32f <= 1;
	always #1 clk_32f <= ~clk_32f;

endmodule

phy/PSRX.v
module PSRX(input clk_4f,
                        input clk_32f,
                        input active,
                        output reg out_serial2_conductual );

    reg [2:0] selector;
    reg [2:0] selector_2;

    always @(posedge clk_32f) begin

      
            if(active == 0) begin
                selector <= 0;
                case (selector_2)
                    0: out_serial2_conductual <= 0;
                    1: out_serial2_conductual <= 1;
                    2: out_serial2_conductual <= 1;
                    3: out_serial2_conductual <= 1;
                    4: out_serial2_conductual <= 1;
                    5: out_serial2_conductual <= 1;
                    6: out_serial2_conductual <= 0;
                    7: begin
                       out_serial2_conductual <= 0;
                        selector_2 <= 0;
                    end
                endcase
                selector_2 <= selector_2 + 1;
            end
            else begin
                selector_2 <= 0;
                case (selector)
                    0: out_serial2_conductual <= 1;
                    1:out_serial2_conductual<= 0;
                    2:out_serial2_conductual <= 1;
                    3:out_serial2_conductual <= 1;
                    4:out_serial2_conductual <= 1;
                    5:out_serial2_conductual <= 1;
                    6:out_serial2_conductual<= 0;
                    7: begin
                       out_serial2_conductual <= 0;
                        selector <= 0;
                    end
                endcase
                selector <= selector + 1;
            end        
        
        
    end
    
endmodule

phy_rx/demux1x2.v
module demux1x2 (output reg [7:0] Salida_conductual0,
            output reg [7:0] Salida_conductual1,
            output reg validsalida0,
            output reg validsalida1,
            
	        input [7:0] Entrada,
            input validEntrada,
            input clk,
            input clk_2f,
            input reset);
            
reg selector;        
        always@(posedge clk) begin
           
       
                if (reset==1)begin //Si el reset es 1 el flop puede tomar el valor de alguna de las dos entradas
                    selector <= ~selector;
                    case(selector)
                        0:  begin
                            
                          if (validEntrada==1)begin
                              
                             Salida_conductual0<=Entrada; // Segun el valor del selector este dato irá a la salida del flop
                             validsalida0<=1;   
                          end

                                else begin
                                Salida_conductual0<=0;
                                end
                
                         
                        end

                        1:   begin
                                if(validEntrada==1)begin 
                                 Salida_conductual1<=Entrada;
                                 validsalida1<=1;  
                                end
                            else begin
                            
                                Salida_conductual1<=0;
                                end
                             //Cambia para tomar entrada 0
                        end
                    endcase
                end    
                else begin
                Salida_conductual0<=0; //Condicion dada en el enunciado, si el reset es cero el flop toma valor de 00
                Salida_conductual1<=0;
                selector<=0;

                end
            end
/*

always@(posedge clk_2f)begin
 selector <= 1;
        if (selector==1)begin
        selector<=0;
        end
        else begin
            selector<=1;
        end
end*/
endmodule

RXParte2/demuxL2.v
//se incluye el mux mas pequeño
`include "demux1x2.v"    
//Se crea el mux de 4 entradas (bus de 8 bits cada una) y 2 salidas(bus de 8 bits),con sus respectivos valid tanto en entradas como salidas
module demuxL2(
	//salida 8 bits
    output [7:0]Salida_conductual0,
    output [7:0]Salida_conductual1,
    
    //salida valid
    output validsalida0,
    output validsalida1,
    
    //entradas
    //2 buses de bits de entrada 8 cada uno
    input [7:0]Entrada,
    
    //2 valids entrada
    input validEntrada,
    
    //clk
    input clk_2f,
    input clk_4f,
        input clk_32f,

    input reset);

    demux1x2 demux1(
        //Salidas
        .Salida_conductual0  (Salida_conductual0[7:0]), 
        .Salida_conductual1 (Salida_conductual1[7:0]),
        .validsalida0 (validsalida0),
        .validsalida1 (validsalida1),
        //Entradas
        .Entrada    (Entrada[7:0]),
        .validEntrada   (validEntrada),
        .clk       (clk_2f),
        .clk_2f   (clk_4f),
        .reset     (reset)
    );
endmodule

phy/demuxL1.v

module demuxL1(
    
    //salida buses de 8 bits 2
    output [7:0]Salida0,
    output [7:0]Salida1,
    output [7:0]Salida2,
    output [7:0]Salida3,
    //salida valids
    output validsalida0,
    output validsalida1,
    output validsalida2,
    output validsalida3,   
    //buses de entrada, 4 de 8 bits
    input [7:0] Entrada0,
    input [7:0] Entrada1,
    
    //valids de entrada 4
    input validEntrada0,
    input validEntrada1,
    
    //reloj
    input clk_f,
    input reset);

    demux1x2 demuxL11(
  //salida 8 bits
    .Salida_conductual0(Salida0[7:0]),
    .Salida_conductual1(Salida1[7:0]),
    
    //salida valid
    .validsalida0(validsalida0),
    .validsalida1(validsalida1),
    
    //entradas
    //2 buses de bits de entrada 8 cada uno
    .Entrada(Entrada0[7:0]),
    
    //2 valids entrada
    .validEntrada(validEntrada0),
    
    //clk
    .clk(clk_f),
    .reset(reset)
    );
    
    demux1x2 demuxL12(
  //salida 8 bits
    .Salida_conductual0(Salida2[7:0]),
    .Salida_conductual1(Salida3[7:0]),
    
    //salida valid
    .validsalida0(validsalida2),
    .validsalida1(validsalida3),
    
    //entradas
    //2 buses de bits de entrada 8 cada uno
    .Entrada(Entrada1[7:0]),
    
    //2 valids entrada
    .validEntrada(validEntrada1),
    
    //clk
    .clk(clk_f),
    .reset(reset)
    );
endmodule

phy_rx/demuxes.v
`include "demuxL2.v"
`include "demuxL1.v"
module demuxes(
                        //salida del L2
                        output [7:0]Salida0,
                       output [7:0]Salida1,
                        output [7:0]Salida2,
                        output [7:0]Salida3,
					    
					    output validsalida0,
                        output validsalida1,
                        output validsalida2,
                        output validsalida3, 
						//output validsalida1,
						
						//valids entrada primero L1
						input [7:0]Entrada,
    
                    //2 valids entrada
                        input validEntrada,
    
						//relojes
                        input clk_32f,
						input clk_4f,
						input clk_2f,
						input clk_f,
						input reset                     
    );
    //SALIDA DEL L1
    wire [7:0] Entrada0, Entrada1;
	wire validsalida0L1, validsalida1L1;
	
		demuxL1 demuxitl1( 
			
			//ENTRADAS
			.clk_f			(clk_2f),
			.reset			(reset),
			
			.validEntrada0	(validsalida0L1),
			.validEntrada1	(validsalida1L1),
			
			.Entrada0		(Entrada0[7:0]), 
			.Entrada1		(Entrada1[7:0]), 
			
			//SALIDAS
			.validsalida0	(validsalida0),
			.validsalida1	(validsalida1),
            .validsalida2	(validsalida2),
            .validsalida3	(validsalida3),
			
			.Salida0		(Salida0[7:0]),
			.Salida1		(Salida1[7:0]),
            .Salida3		(Salida2[7:0]),
			.Salida2		(Salida3[7:0])
			);


		demuxL2 demuxitoL2( 
			
			//ENTRADAS
			.Entrada			(Entrada[7:0]),
			
            .validEntrada (validEntrada),

				.clk_2f				(clk_2f),
			.clk_4f				(clk_4f),
            .clk_32f				(clk_32f),
			.reset 				(reset),
			//Salidas
			.Salida_conductual0	    (Entrada0 [7:0]),
			.Salida_conductual1		(Entrada1[7:0]),
            .validsalida0(validsalida0L1),
            .validsalida1(validsalida1L1)
           
		
			);
			
endmodule

phy_rx/serial_paraleloRX.v

module serial_paraleloRX(
	//ENTRADAS
			
			input data_in,			//entrada de datos
			input reset,			//
			input clk_32f,			//clock frecuencia 32
			input clk_4f,			//clock frecuencia 4
	//SALIDAS
	
			output reg	[7:0] data_serial_paraleloRX, 	//salida RX
			output reg	active_serial_paraleloRX,		//active
			output reg  valid_serial_paraleloRX			//valid
						
);
			reg [7:0] buffer;					//guarda datos actuales (n)
			reg [7:0] buffer_pasado;			//guarda datos pasados (n-1)
			
			integer contador;					//
			integer contador_BC;				//contador de datos BC entrada*se buscan 4

	always @(posedge clk_32f)
	
	begin
			if( reset == 0) 
			
			begin
				
				data_serial_paraleloRX [7:0] <= 8'b00000000;
				active_serial_paraleloRX <= 0;
				valid_serial_paraleloRX	<= 0;
				buffer <= 0;
				contador <= 0;
				contador_BC <= 0;
			end
			
			else
			begin
				buffer <= {buffer[7:0], data_in};	//en buffer se concatena al ultimo bit de posicion el dato se va llenando de esta manera 
				
				if (contador_BC == 4 && contador == 1)
				begin
					
					active_serial_paraleloRX <= 1;
					
					if (buffer != 8'hBC)
					
					begin
						
						valid_serial_paraleloRX	<= 1;
						data_serial_paraleloRX <= buffer;
					end
					
					else if (buffer_pasado != 8'hBC && buffer == 8'hBC)
					
					begin
						
						valid_serial_paraleloRX	<= 0;
						contador_BC <= 0;
						
					end
			end
				
				if (contador_BC < 4 && buffer == 8'hBC)
				
				begin
					
						valid_serial_paraleloRX	<= 0;
						data_serial_paraleloRX <= 0;
						contador_BC <= contador_BC + 1;
				end
					
				if (contador == 1)
				begin
						buffer_pasado <=buffer;
				end
				
				if (contador == 7)
				begin
						contador <= 0;
				end
				
				else if (contador != 7)
				begin
						contador <= contador + 1;
				end
		end
	end
endmodule

phy/phy_rx.v
`include "serial_paraleloRX.v"
`include "demuxes.v"
`include "PSRX.v"


module Rx(  input data_in,
            input clk_32f,
            input clk_4f,
            input clk_2f,
			input clk_f,
            input reset,
            output [7:0] out0,
            output [7:0] out1,
            output [7:0] out2,
            output [7:0] out3,
            output [7:0] data_serial_paraleloRX,

            output valid_datademuxL20,
            output valid_datademuxL21,
            output valid_datademuxL22,
            output valid_datademuxL23,            

            output out_serial2_conductual        
);

wire [7:0] data_serial_paraleloRX;
wire [15:0] salidaL1;
wire [7:0] salida1, salida2,salida3,salida4;
wire active_serial_paraleloRX,valid_serial_paraleloRX,valid_datademuxl10,valid_datademuxl11;


serial_paraleloRX serialparalelo(/*AUTOINST*/
				    // ENTRADAS
				    .reset		(reset),
				    .clk_4f		(clk_4f),
				    .clk_32f		(clk_32f),
				    .data_in		(data_in),
				    
				    // SALIDAS
				    .data_serial_paraleloRX		(data_serial_paraleloRX[7:0]),
				    .active_serial_paraleloRX	(active_serial_paraleloRX),
				    .valid_serial_paraleloRX	(valid_serial_paraleloRX)
                );



    demuxes demuxes(.Salida0	(out0[7:0]),
            .Salida1	(out1[7:0]),
             .Salida2	(out2[7:0]),
             .Salida3	(out3[7:0]),

		     .validsalida0	(valid_datademuxL20),
             .validsalida1	(valid_datademuxL21),
            .validsalida2	(valid_datademuxL22),
             .validsalida3	(valid_datademuxL23),

		     // Inputs
		     .validEntrada	(valid_serial_paraleloRX),
		     .Entrada(data_serial_paraleloRX[7:0]),

		     .clk_4f		(clk_4f),
		     .clk_2f		(clk_2f),
		     .clk_f		(clk_f),
                .clk_32f (clk_32f),

		     .reset		(reset));





    PSRX    Paralelo(   .clk_4f(clk_4f),
                        .clk_32f(clk_32f),
                        .active(active_serial_paraleloRX),
                        .out_serial2_conductual(out_serial2_conductual)
                        );


endmodule

phy_rx/BancoRX.v
`timescale 1ms/100ps
`include "phy_rx.v"
`include "probador_RX.v"

module BancoPruebas;

		wire data_in;
		wire clk_4f;
		wire clk_32f;
        wire clk_2f;
        wire [7:0] data_serial_paraleloRX;
        wire reset;
        wire [7:0] Salida0,Salida1,Salida2,Salida3;
        wire validSalida0, validSalida1,validSalida2,validSalida3,out_serial2_conductual;
        


        Rx RX(

            .data_in(data_in),
            .clk_32f(clk_32f),
            .clk_4f(clk_4f),
            .clk_2f(clk_2f),
            .clk_f(clk_f),
            .data_serial_paraleloRX(data_serial_paraleloRX[7:0]),
            .reset(reset),
            .out0(Salida0[7:0]),
            .out1(Salida1),
            .out2(Salida2),
            .out3(Salida3),
            .valid_datademuxL20(validSalida0),
            .valid_datademuxL21(validSalida1),
            .valid_datademuxL22(validSalida2),
            .valid_datademuxL23(validSalida3),
                        

            .out_serial2_conductual()        
            );
        probador_serial_paraleloRX Probador(
            .data_in(data_in),			//entrada de datos a 32f
	        .reset(reset),			//
			.clk_32f(clk_32f),			//clock frecuencia 32
			.clk_4f(clk_4f),
            .clk_2f(clk_2f),
            .clk_f(clk_f),
            .validSalida0(validSalida0),
            .validSalida1(validSalida1),
            .validSalida2(validSalida2),
            .validSalida3(validSalida3),
            .Salida0(Salida0),
            .Salida1(Salida1),
            .Salida2(Salida2),
            .Salida3(Salida3),
            .out_serial2_conductual(out_serial2_conductual)



        );

endmodule

phy_rx/RX.vcd
$date
	Sat Jun 12 15:37:52 2021
$end
$version
	Icarus Verilog
$end
$timescale
	100ps
$end
$scope module BancoPruebas $end
$var wire 1 ! out_serial2_conductual $end
$var wire 1 " validSalida3 $end
$var wire 1 # validSalida2 $end
$var wire 1 $ validSalida1 $end
$var wire 1 % validSalida0 $end
$var wire 1 & reset $end
$var wire 8 ' data_serial_paraleloRX [7:0] $end
$var wire 1 ( data_in $end
$var wire 1 ) clk_f $end
$var wire 1 * clk_4f $end
$var wire 1 + clk_32f $end
$var wire 1 , clk_2f $end
$var wire 8 - Salida3 [7:0] $end
$var wire 8 . Salida2 [7:0] $end
$var wire 8 / Salida1 [7:0] $end
$var wire 8 0 Salida0 [7:0] $end
$scope module Probador $end
$var wire 8 1 Salida0s [7:0] $end
$var wire 8 2 Salida1s [7:0] $end
$var wire 8 3 Salida2s [7:0] $end
$var wire 8 4 Salida3s [7:0] $end
$var wire 1 ! out_serial2_conductual $end
$var wire 1 5 out_serial2_conductual_s $end
$var wire 1 6 validSalida0s $end
$var wire 1 7 validSalida1s $end
$var wire 1 8 validSalida2s $end
$var wire 1 9 validSalida3s $end
$var wire 1 " validSalida3 $end
$var wire 1 # validSalida2 $end
$var wire 1 $ validSalida1 $end
$var wire 1 % validSalida0 $end
$var wire 8 : Salida3 [7:0] $end
$var wire 8 ; Salida2 [7:0] $end
$var wire 8 < Salida1 [7:0] $end
$var wire 8 = Salida0 [7:0] $end
$var reg 1 , clk_2f $end
$var reg 1 + clk_32f $end
$var reg 1 * clk_4f $end
$var reg 1 ) clk_f $end
$var reg 1 ( data_in $end
$var reg 1 & reset $end
$upscope $end
$scope module RX $end
$var wire 1 , clk_2f $end
$var wire 1 + clk_32f $end
$var wire 1 * clk_4f $end
$var wire 1 ) clk_f $end
$var wire 1 ( data_in $end
$var wire 1 & reset $end
$var wire 1 > valid_serial_paraleloRX $end
$var wire 1 " valid_datademuxL23 $end
$var wire 1 # valid_datademuxL22 $end
$var wire 1 $ valid_datademuxL21 $end
$var wire 1 % valid_datademuxL20 $end
$var wire 1 ? out_serial2_conductual $end
$var wire 8 @ out3 [7:0] $end
$var wire 8 A out2 [7:0] $end
$var wire 8 B out1 [7:0] $end
$var wire 8 C out0 [7:0] $end
$var wire 8 D data_serial_paraleloRX [7:0] $end
$var wire 1 E active_serial_paraleloRX $end
$scope module Paralelo $end
$var wire 1 + clk_32f $end
$var wire 1 * clk_4f $end
$var wire 1 E active $end
$var reg 1 ? out_serial2_conductual $end
$var reg 3 F selector [2:0] $end
$var reg 3 G selector_2 [2:0] $end
$upscope $end
$scope module demuxes $end
$var wire 1 , clk_2f $end
$var wire 1 + clk_32f $end
$var wire 1 * clk_4f $end
$var wire 1 ) clk_f $end
$var wire 1 & reset $end
$var wire 1 " validsalida3 $end
$var wire 1 # validsalida2 $end
$var wire 1 H validsalida1L1 $end
$var wire 1 $ validsalida1 $end
$var wire 1 I validsalida0L1 $end
$var wire 1 % validsalida0 $end
$var wire 1 > validEntrada $end
$var wire 8 J Salida3 [7:0] $end
$var wire 8 K Salida2 [7:0] $end
$var wire 8 L Salida1 [7:0] $end
$var wire 8 M Salida0 [7:0] $end
$var wire 8 N Entrada1 [7:0] $end
$var wire 8 O Entrada0 [7:0] $end
$var wire 8 P Entrada [7:0] $end
$scope module demuxitl1 $end
$var wire 1 , clk_f $end
$var wire 1 & reset $end
$var wire 1 " validsalida3 $end
$var wire 1 # validsalida2 $end
$var wire 1 $ validsalida1 $end
$var wire 1 % validsalida0 $end
$var wire 1 H validEntrada1 $end
$var wire 1 I validEntrada0 $end
$var wire 8 Q Salida3 [7:0] $end
$var wire 8 R Salida2 [7:0] $end
$var wire 8 S Salida1 [7:0] $end
$var wire 8 T Salida0 [7:0] $end
$var wire 8 U Entrada1 [7:0] $end
$var wire 8 V Entrada0 [7:0] $end
$scope module demuxL11 $end
$var wire 1 , clk $end
$var wire 1 W clk_2f $end
$var wire 1 & reset $end
$var wire 1 I validEntrada $end
$var wire 8 X Entrada [7:0] $end
$var reg 8 Y Salida_conductual0 [7:0] $end
$var reg 8 Z Salida_conductual1 [7:0] $end
$var reg 1 [ selector $end
$var reg 1 % validsalida0 $end
$var reg 1 $ validsalida1 $end
$upscope $end
$scope module demuxL12 $end
$var wire 1 , clk $end
$var wire 1 \ clk_2f $end
$var wire 1 & reset $end
$var wire 1 H validEntrada $end
$var wire 8 ] Entrada [7:0] $end
$var reg 8 ^ Salida_conductual0 [7:0] $end
$var reg 8 _ Salida_conductual1 [7:0] $end
$var reg 1 ` selector $end
$var reg 1 # validsalida0 $end
$var reg 1 " validsalida1 $end
$upscope $end
$upscope $end
$scope module demuxitoL2 $end
$var wire 1 , clk_2f $end
$var wire 1 + clk_32f $end
$var wire 1 * clk_4f $end
$var wire 1 & reset $end
$var wire 1 H validsalida1 $end
$var wire 1 I validsalida0 $end
$var wire 1 > validEntrada $end
$var wire 8 a Salida_conductual1 [7:0] $end
$var wire 8 b Salida_conductual0 [7:0] $end
$var wire 8 c Entrada [7:0] $end
$scope module demux1 $end
$var wire 1 * clk $end
$var wire 1 d clk_2f $end
$var wire 1 & reset $end
$var wire 1 > validEntrada $end
$var wire 8 e Entrada [7:0] $end
$var reg 8 f Salida_conductual0 [7:0] $end
$var reg 8 g Salida_conductual1 [7:0] $end
$var reg 1 h selector $end
$var reg 1 I validsalida0 $end
$var reg 1 H validsalida1 $end
$upscope $end
$upscope $end
$upscope $end
$scope module serialparalelo $end
$var wire 1 + clk_32f $end
$var wire 1 * clk_4f $end
$var wire 1 ( data_in $end
$var wire 1 & reset $end
$var reg 1 E active_serial_paraleloRX $end
$var reg 8 i buffer [7:0] $end
$var reg 8 j buffer_pasado [7:0] $end
$var reg 8 k data_serial_paraleloRX [7:0] $end
$var reg 1 > valid_serial_paraleloRX $end
$var integer 32 l contador [31:0] $end
$var integer 32 m contador_BC [31:0] $end
$upscope $end
$upscope $end
$upscope $end
$enddefinitions $end
#0
$dumpvars
bx m
bx l
bx k
bx j
bx i
0h
b0 g
b0 f
bx e
zd
bx c
b0 b
b0 a
x`
bx _
bx ^
b0 ]
z\
x[
bx Z
bx Y
b0 X
zW
b0 V
b0 U
bx T
bx S
bx R
bx Q
bx P
b0 O
b0 N
bx M
bx L
bx K
bx J
xI
xH
b0 G
bx F
xE
bx D
bx C
bx B
bx A
bx @
x?
x>
bx =
bx <
bx ;
bx :
z9
z8
z7
z6
z5
bz 4
bz 3
bz 2
bz 1
bx 0
bx /
bx .
bx -
0,
1+
1*
0)
x(
bx '
x&
x%
x$
x#
x"
z!
$end
#10000000
0+
#20000000
1+
#30000000
0+
#40000000
1+
#50000000
0+
#60000000
1+
#70000000
0+
#80000000
1+
0*
#90000000
0+
#100000000
1+
#110000000
0+
#120000000
1+
#130000000
0+
#140000000
1+
#150000000
0+
#160000000
0[
b0 /
b0 <
b0 B
b0 L
b0 S
b0 Z
b0 0
b0 =
b0 C
b0 M
b0 T
b0 Y
0`
b0 .
b0 ;
b0 A
b0 K
b0 Q
b0 _
b0 -
b0 :
b0 @
b0 J
b0 R
b0 ^
1+
1*
1,
#170000000
0+
#180000000
1+
#190000000
0+
#200000000
1+
#210000000
0+
#220000000
1+
#230000000
0+
#240000000
1+
0*
#250000000
0+
#260000000
1+
#270000000
0+
#280000000
1+
#290000000
0+
#300000000
1+
#310000000
0+
#320000000
1(
0&
1+
1*
0,
1)
#330000000
0+
#340000000
0(
b0 m
b0 l
b0 i
0>
0E
b0 '
b0 D
b0 P
b0 c
b0 e
b0 k
1+
#350000000
0+
#360000000
b1 G
0?
b0 F
1(
1+
#370000000
0+
#380000000
b10 G
1?
1+
#390000000
0+
#400000000
b11 G
1+
0*
#410000000
0+
#420000000
b100 G
1+
#430000000
0+
#440000000
b101 G
0(
1+
#450000000
0+
#460000000
b110 G
1+
#470000000
0+
#480000000
b111 G
0?
1+
1*
1,
#490000000
0+
#500000000
b0 G
1+
#510000000
0+
#520000000
b1 G
1(
1+
#530000000
0+
#540000000
b10 G
1?
1+
#550000000
0+
#560000000
b11 G
1+
0*
#570000000
0+
#580000000
b100 G
1+
#590000000
0+
#600000000
b101 G
0(
1+
#610000000
0+
#620000000
b110 G
1+
#630000000
0+
#640000000
b111 G
0?
1+
1*
0,
0)
#650000000
0+
#660000000
b0 G
1+
#670000000
0+
#680000000
b1 G
1+
#690000000
0+
#700000000
b10 G
1?
1+
#710000000
0+
#720000000
b11 G
1+
0*
#730000000
0+
#740000000
b100 G
1+
#750000000
0+
#760000000
b101 G
1+
#770000000
0+
#780000000
b110 G
1+
#790000000
0+
#800000000
b111 G
0?
1+
1*
1,
#810000000
0+
#820000000
b0 G
1+
#830000000
0+
#840000000
b1 G
1+
#850000000
0+
#860000000
b10 G
1?
1+
#870000000
0+
#880000000
b11 G
1+
0*
#890000000
0+
#900000000
b100 G
1+
#910000000
0+
#920000000
b101 G
1+
#930000000
0+
#940000000
b110 G
1+
