phy_tx/probador_Tx.v
//Módulo donde se generan los datos para realizar las pruebas a la conexión del phy_tx


module probador_tx (

	output reg [7:0] data_in0,   //DATOS DE ENTRADA
	output reg [7:0] data_in1,   //BUSES DE 8 BITS X 4
	output reg [7:0] data_in2,
	output reg [7:0] data_in3,

    output reg valid0,   //VALIDS DE ENTRADA X4
	output reg valid1,
	output reg valid2,
	output reg valid3,       

    output reg reset,    //RESET
    output reg active,
    output reg out_serial2_conductual, //entrada IDLIN de serial a conductual 

    output reg clk_2f,  //RELOJ 2F
	output reg clk_f,    //RELOJ F
	output reg clk_4f,   //RELOJ 4F
	//////
    input out_serial_conductual, //SALIDA DEL PARALELO-SERIAL A EL MODULO RX
    
    input [7:0] recirculador_desactivado0,  //SALIDA PARA EL PROBADOR
    input [7:0] recirculador_desactivado1,
    input [7:0] recirculador_desactivado2,
    input [7:0] recirculador_desactivado3
    );
    
    initial begin
	$dumpfile("PHYTX.vcd");
	$dumpvars;
    active<=1;
	{valid0,valid1,valid2,valid3, reset, out_serial2_conductual} <= 0;
	{data_in0} <= 8'h00;
    {data_in1} <= 8'hEE;
    {data_in2} <= 8'hFF;
    {data_in3} <= 8'hFD;
    
	@(posedge clk_f);
	//active <= 1;

	valid0 <= 1;
	valid1 <= 1;
	valid2 <= 1;
	valid3 <= 1;
	data_in1 <= 8'hCC;
	data_in1 <= 8'hFD;
    data_in2 <= 8'hAA;
    data_in3 <= 8'h12;
    @(posedge clk_2f);
    @(posedge clk_4f);
    @(posedge clk_4f);
    @(posedge clk_2f);



	@(posedge clk_f);
	//active <= 1;
	valid0 <= 1;
	valid1 <= 1;
	valid2 <= 1;
	valid3 <= 1;
	data_in1 <= 8'hCC;
	data_in1 <= 8'hF0;
    data_in2 <= 8'hAA;
    data_in3 <= 8'h11;
   @(posedge clk_2f);
    @(posedge clk_4f);
    @(posedge clk_4f);
    @(posedge clk_2f);
	@(posedge clk_f);
	reset <= 1;
	//active <= 1;
	valid0 <= 1;
	valid1 <= 1;
	valid2 <= 1;
	valid3 <= 1;
	data_in1 <= 8'hCA;
	data_in1 <= 8'hF2;
    data_in2 <= 8'hAA;
    data_in3 <= 8'h12;

   @(posedge clk_2f);
    @(posedge clk_4f);
    @(posedge clk_4f);
    @(posedge clk_2f);

	@(posedge clk_f);
	//active <= 1;
	valid0 <= 1;
	valid1 <= 1;
	valid2 <= 1;
	valid3 <= 1;
	data_in1 <= 8'hCA;
	data_in1 <= 8'hF2;
    data_in2 <= 8'hbA;
    data_in3 <= 8'h12;

   @(posedge clk_2f);
    @(posedge clk_4f);
    @(posedge clk_4f);
    @(posedge clk_2f);


	@(posedge clk_f);
	//active <= 1;
	valid0 <= 0;
	valid1 <= 0;
	valid2 <= 0;
	valid3 <= 0;
	data_in1 <= 8'hCA;
	data_in1 <= 8'hF2;
    data_in2 <= 8'hA1;
    data_in3 <= 8'h12;

   @(posedge clk_2f);
    @(posedge clk_4f);
    @(posedge clk_4f);
    @(posedge clk_2f);
	@(posedge clk_f);
	//active <= 1;
	valid0 <= 0;
	valid1 <= 0;
	valid2 <= 0;
	valid3 <= 0;
	data_in1 <= 8'hCA;
	data_in1 <= 8'hF2;
    data_in2 <= 8'h11;
    data_in3 <= 8'h12;
    
	@(posedge clk_f);
	//active <= 0;
	valid0 <= 1;
	valid1 <= 1;
	valid2 <= 1;
	valid3 <= 1;
	data_in1 <= 8'hCA;
	data_in1 <= 8'hF2;
    data_in2 <= 8'hAA;
    data_in3 <= 8'h12;

	@(posedge clk_f);

	@(posedge clk_f);
	
	@(posedge clk_f);
	
	@(posedge clk_f);
	
	@(posedge clk_f);
	$finish;
	end
	
	initial clk_f <= 1;
	initial clk_2f <= 1;
	initial clk_4f <= 1;
	

	always #24 clk_f <= ~clk_f;
	always #16 clk_2f <= ~clk_2f;
	always #8 clk_4f <= ~clk_4f;
	
	


endmodule

phy_tx/serialparalelotx.v
module serialparalelotx(
	//ENTRADAS
			
			input IDLin,			//entrada de datos
			input reset,			//
			input clk_32f,			//clock frecuencia 32
			input clk_4f,			//clock frecuencia 4
	//SALIDAS
	
			output reg	[7:0] data_serial_paraleloTX, 		//salida RX
			output reg	active_serial_paraleloTX,		//active
			output reg  IDLEOut			//valid
						
);
			reg [7:0] buffer;					//guarda datos actuales (n)
			reg [7:0] buffer_pasado;			//guarda datos pasados (n-1)
			
			integer contador;					//
			integer contador_BC;				//contador de datos BC entrada*se buscan 4

	always @(posedge clk_32f)
	
	begin
			if( reset == 0) 
			
			begin
				
				data_serial_paraleloTX [6:0] <= 8'b00000000;
				active_serial_paraleloTX <= 0;
				IDLEOut	<= 0;
				buffer <= 0;
				contador <= 0;
				contador_BC <= 0;
			end
			
			else
			begin
				buffer <= {buffer[6:0], IDLin};	//en buffer se concatena al ultimo bit de posicion el dato se va llenando de esta manera 
				
				if (contador_BC == 4 && contador == 1)
				begin
					
					active_serial_paraleloTX <= 1;
					
					if (buffer != 8'hBC)
					
					begin
						
						IDLEOut	<= 1;
						data_serial_paraleloTX <= buffer;
					end
					
					else if (buffer_pasado != 8'hBC && buffer == 8'hBC)
					
					begin
						
						IDLEOut	<= 0;
						contador_BC <= 0;
						
					end
			end
				
				if (contador_BC < 4 && buffer == 8'hBC)
				
				begin
					
						IDLEOut	<= 0;
						data_serial_paraleloTX <= 0;
						contador_BC <= contador_BC + 1;
				end
					
				if (contador == 1)
				begin
						buffer_pasado <=buffer;
				end
				
				if (contador == 7)
				begin
						contador <= 0;
				end
				
				else if (contador != 7)
				begin
						contador <= contador + 1;
				end
		end
	end
endmodule

phy_tx/paralelo_serial.v

module paralelo_serial(
    input reset,
    input clk_4f,
    input clk_32f,
    input valid_in,
    input [7:0] in_serial,
    output reg out_serial_conductual);

    reg [2:0] selector;
    reg [2:0] selector_2;

    always @(posedge clk_32f) begin

        if (reset == 1) begin
            if(valid_in == 1) begin
                selector <= 0;
                case (selector_2)
                    0: out_serial_conductual <= in_serial[7];
                    1: out_serial_conductual <= in_serial[6];
                    2: out_serial_conductual <= in_serial[5];
                    3: out_serial_conductual <= in_serial[4];
                    4: out_serial_conductual <= in_serial[3];
                    5: out_serial_conductual <= in_serial[2];
                    6: out_serial_conductual <= in_serial[1];
                    7: begin
                        out_serial_conductual <= in_serial[0];
                        selector_2 <= 0;
                    end
                endcase
                selector_2 <= selector_2 + 1;
            end
            else begin
                selector_2 <= 0;
                case (selector)
                    0:out_serial_conductual <= 1;
                    1:out_serial_conductual <= 0;
                    2:out_serial_conductual <= 1;
                    3:out_serial_conductual <= 1;
                    4:out_serial_conductual <= 1;
                    5:out_serial_conductual <= 1;
                    6:out_serial_conductual <= 0;
                    7: begin
                       out_serial_conductual <= 0;
                        selector <= 0;
                    end
                endcase
                selector <= selector + 1;
            end
        end
        
        else begin
            out_serial_conductual <= 0;
            {selector, selector_2} <= 0;
        end
    end
endmodule

phy_tx/mux2x1.v


module mux2x1 (output reg [7:0] Salida_conductual,
            input validsalida,
	        input [7:0] Entrada0,
            input [7:0] Entrada1,
            input validEntrada0,
            input validEntrada1,
            input clk,
            input reset);
            
reg selector;        

always@(posedge clk) begin
           
    if (reset==1)begin //Si el reset es 1 el flop puede tomar el valor de alguna de las dos entradas
        selector <= 0;

        case(selector)
        
            0:  begin
                if (validEntrada0==1)
                    Salida_conductual<=Entrada0; // Segun el valor del selector este dato irá a la salida del flop
                else begin
                    Salida_conductual<=0;
                end
                                
                selector <= 1;  //Cambia para toamr Entrada1
                end

            1:   begin
                if(validEntrada1==1)
                    Salida_conductual<=Entrada1;
                else begin
                    Salida_conductual<=0;
                end
                    selector<=0;//Cambia para tomar entrada 0
                end

        endcase
    end    

    else begin
        Salida_conductual<=0; //Condicion dada en el enunciado, si el reset es cero el flop toma valor de 00
        selector<=0;
    end
end

endmodule

phy_tx/muxL2.v
//se incluye el mux mas pequeño
`include "mux2x1.v"    
//Se crea el mux de 4 entradas (bus de 8 bits cada una) y 2 salidas(bus de 8 bits),con sus respectivos valid tanto en entradas como salidas
module muxL2(
	//salida 8 bits
    output [7:0]Salida_conductual,
    //salida valid
    output validsalida,
    
    //entradas
    //2 buses de bits de entrada 8 cada uno
    input [7:0]Entrada0,
    input [7:0]Entrada1,
    
    //2 valids entrada
    input validEntrada0,
    input validEntrada1,
    
    //clk
    input clk_4f,
    input reset);

    mux2x1 mux1(
        //Salidas
        .Salida_conductual  (Salida_conductual[7:0]),  
        .validsalida (validsalida),
        //Entradas
        .Entrada0    (Entrada0[7:0]),
        .Entrada1   (Entrada1[7:0]),
        .validEntrada0   (validEntrada0),
        .validEntrada1    (validEntrada1),
        .clk       (clk_4f),
        .reset     (reset)
    );
endmodule

phy_tx/muxL1.v
//Se incluye el mux mas pequeño
`include "mux2x1.v"
//Se crea el mux de 4 entradas (bus de 8 bits cada una) y 2 salidas(bus de 8 bits),con sus respectivos valid tanto en entradas como salidas

module muxL1(
    output [7:0]Salida0,
    output [7:0]Salida1,
    
    output validsalida1,
    output validsalida0,

    input [7:0]Entrada0,
    input [7:0]Entrada1,
    input [7:0]Entrada2,
    input [7:0]Entrada3,
    input validEntrada0,
    input validEntrada1,
    input validEntrada2,
    input validEntrada3,
    
    input clk_2f,
    input reset);

    mux2x1 mux1(
        //Salidas
        .Salida_conductual  (Salida0[7:0]),  
        .validsalida    (validsalida0),
        //Entradas
        .Entrada0       (Entrada0[7:0]),
        .Entrada1       (Entrada1[7:0]),
        .validEntrada0  (validEntrada0),
        .validEntrada1  (validEntrada1),

        .clk            (clk_2f),
        .reset          (reset)
    );
    mux2x1 mux2(
        //Salidas
        .Salida_conductual  (Salida1[7:0]),  
        .validsalida    (validsalida1),
        //Entradas
        .Entrada0       (Entrada2[7:0]),
        .Entrada1       (Entrada3[7:0]),
        .validEntrada0  (validEntrada2),
        .validEntrada1  (validEntrada3),

        .clk       (clk_2f),
        .reset     (reset)
    );

endmodule

phy_tx/Muxes.v
`include "./muxL2.v"
`include "./muxL1.v"
module Muxes(
                        //salida del L2
                        output  [7:0] Salida_conductual,
					    
					    output validsalida,
						//output validsalida1,
						
						//valids entrada primero L1
						input validEntrada0,
                        input validEntrada1,
                        input validEntrada2,
                        input validEntrada3,
                        
                        //entrada L1 DATOS
                        input [7:0] Entrada0,
						input [7:0] Entrada1,
                        input [7:0] Entrada2,
						input [7:0] Entrada3,
						
						//relojes
						input clk_4f,
						input clk_2f,
						input clk_f,
						input reset                     
    );
    //SALIDA DEL L1
    wire [7:0] Salida0, Salida1;
	wire validsalida0, validsalida1;
	
		muxL1 muxl1( 
			
			//ENTRADAS
			.clk_2f			(clk_2f),
			.reset			(reset),
			
			.validEntrada0	(validEntrada0),
			.validEntrada1	(validEntrada1),
			.validEntrada2	(validEntrada2),
			.validEntrada3	(validEntrada3),
			
			.Entrada0		(Entrada2[7:0]), 
			.Entrada1		(Entrada3[7:0]), 
			.Entrada2		(Entrada0[7:0]), 
			.Entrada3		(Entrada1[7:0]), 
			
			//SALIDAS
			.validsalida0	(validsalida0),
			.validsalida1	(validsalida1),
			
			.Salida0		(Salida0[7:0]),
			.Salida1		(Salida1[7:0])
			);


		muxL2 muxitol2( 
			
			//ENTRADAS
			.Entrada0			(Salida0	[7:0]),
			.Entrada1			(Salida1 	[7:0]),
			
			.validEntrada0		(validsalida0),
			.validEntrada1		(validsalida1),
			
			.clk_4f				(clk_4f),
			.reset 				(reset),
			
			.Salida_conductual	(Salida_conductual [7:0]),
			.validsalida		(validsalida0)
		
			);
			
endmodule

phy_tx/recirculador.v
//PRIMER AVANCE

module recirculador(
	//ETAPA FLOPS
	//SE TIENEN 8x4 bits de entrada (32 bits) y un bit para valid 4 entradas
	input [7:0] data_in0,
	input [7:0] data_in1,
	input [7:0] data_in2,
	input [7:0] data_in3,
	input valid0,
	input valid1,
	input valid2,
	input valid3,

	//clock
	input clk,
	//senal de activacion
	input reset,
	
	//entrada active viene del bloque serial a pararelo no se define aun su contenido
	input active,
	
	//SALIDAS 32 BITS
	output reg valid_out_recirculador0,
	output reg valid_out_recirculador1,
	output reg valid_out_recirculador2,
	output reg valid_out_recirculador3,
	
	//activo se dirige la logica al mux L1
	output reg [7:0] recirculador_activo0,
	output reg [7:0] recirculador_activo1,
	output reg [7:0] recirculador_activo2,
	output reg [7:0] recirculador_activo3,
	
	//inactivo se dirige la logica hacia el probador
	output reg [7:0] recirculador_desactivado0,
	output reg [7:0] recirculador_desactivado1,
	output reg [7:0] recirculador_desactivado2,
	output reg [7:0] recirculador_desactivado3
	
);

	always @(posedge clk) 
	
	begin
		
		if (reset==0)			//si reset es 0 se asigna un 0 en salida valid
			begin				//info de entrada se asigna a recirculador para salida inactivo
					
					valid_out_recirculador0 <= 0;
					valid_out_recirculador1 <= 0;
					valid_out_recirculador2 <= 0;
					valid_out_recirculador3 <= 0;
					
					recirculador_desactivado0 <= 0;
					recirculador_desactivado1 <= 0;
					recirculador_desactivado2 <= 0;
					recirculador_desactivado3 <= 0;
					
					recirculador_activo0 <= 0;
					recirculador_activo1 <= 0;
					recirculador_activo2 <= 0;
					recirculador_activo3 <= 0;
			
			end
		
		else if(reset ==1)		//si el reset es uno se analizan el flujo de datos *act
			begin
			
			if(valid0==1 && active==1)
			
				recirculador_activo0 <= data_in0;
				valid_out_recirculador0 <= 1;
				
			if(valid1==1 && active==1)
				
				recirculador_activo1 <= data_in1;
				valid_out_recirculador1 <= 1;
				
			if(valid2==1 && active==1)
			
				recirculador_activo2 <= data_in2;
				valid_out_recirculador2 <= 1;
				
			if(valid3==1 && active==1)
				
				recirculador_activo3 <= data_in3;
				
				valid_out_recirculador3 <= 1;
				
			if	(active==0)

					recirculador_desactivado0 <= 0;
					recirculador_desactivado1 <= 0;
					recirculador_desactivado2 <= 0;
					recirculador_desactivado3 <= 0;			
				
				
			end	 	
	
	end
	
endmodule

phy_tx/phy_tx.v
`include "recirculador.v"
`include "Muxes.v"
`include "paralelo_serial.v"
`include "serialparalelotx.v"

module phy_tx (
    input [7:0] data_in0,   //DATOS DE ENTRADA
	input [7:0] data_in1,   //BUSES DE 8 BITS X 4
	input [7:0] data_in2,
	input [7:0] data_in3,

    input valid0,   //VALIDS DE ENTRADA X4
	input valid1,
	input valid2,
	input valid3,       

    input reset,    //RESET
    input active,
    input out_serial2_conductual, //entrada IDLIN de serial a conductual 

    input clk_2f,  //RELOJ 2F
	input clk_f,    //RELOJ F
	input clk_4f,   //RELOJ 4F

    output out_serial_conductual, //SALIDA DEL PARALELO-SERIAL A EL MODULO RX
    
    output [7:0] recirculador_desactivado0,  //SALIDA PARA EL PROBADOR
    output [7:0] recirculador_desactivado1,
    output [7:0] recirculador_desactivado2,
    output [7:0] recirculador_desactivado3
);
    //BLOQUE1
    wire [7:0] Entrada0;    //salidas del recirculador
    wire [7:0] Entrada1;    //datos
    wire [7:0] Entrada2;    //entrada del muxL1
    wire [7:0] Entrada3;

    wire valid_out_recirculador0;   //salidas de valids
	wire valid_out_recirculador1;   // del recirculador
	wire valid_out_recirculador2;   //son tambien entradas
	wire valid_out_recirculador3;   //del mux L1

    
    //BLOQUE3
    wire [7:0] Salida_conductual;   //datos salida del L2
    wire validsalida;               //salida valid del L2
                                    //entrada paralelo a serial
    
    //SERIAL A PARALELO TX
    //input out_serial2_conductual es la entrada
    wire [7:0] data_serial_paraleloRX;      //salida de 8 bits de SaP
    //wire active;          //
    wire IDLEOut;

recirculador recirculadorphy(
    /*AUTOINST*/
                //ENTRADAS
                
                .clk      		(clk_f),
                .data_in0       (data_in0),
                .data_in1       (data_in1),
                .data_in2       (data_in2),
                .data_in3       (data_in3),

                .valid0         (valid0),
                .valid1         (valid1),
                .valid2         (valid2),
                .valid3         (valid3),

                .reset          (reset),
                .active         (active),

                //SALIDAS

                .recirculador_activo0   (Entrada0 [7:0]),
                .recirculador_activo1   (Entrada1 [7:0]),
                .recirculador_activo2   (Entrada2 [7:0]),
                .recirculador_activo3   (Entrada3 [7:0]),

                .recirculador_desactivado0  (recirculador_desactivado0 [7:0]),
                .recirculador_desactivado1  (recirculador_desactivado1 [7:0]),
                .recirculador_desactivado2  (recirculador_desactivado2 [7:0]),
                .recirculador_desactivado3  (recirculador_desactivado3 [7:0]),

                .valid_out_recirculador0    (valid_out_recirculador0),
                .valid_out_recirculador1    (valid_out_recirculador1),
                .valid_out_recirculador2    (valid_out_recirculador2),
                .valid_out_recirculador3    (valid_out_recirculador3)

);

Muxes muxess(
			/*AUTOINST*/
			//ENTRADAS
			.validEntrada0	(valid_out_recirculador0),
			.validEntrada1	(valid_out_recirculador1),
			.validEntrada2	(valid_out_recirculador2),
			.validEntrada3	(valid_out_recirculador3),
			
			.clk_4f			(clk_4f),
			.clk_2f			(clk_2f),
			.clk_f			(clk_f),
			.reset  		(reset),
			
			.Entrada0		(Entrada0),
			.Entrada1		(Entrada1),
			.Entrada2		(Entrada2),
			.Entrada3		(Entrada3),
			
			//SALIDAS
			.Salida_conductual	(Salida_conductual [7:0]),
			.validsalida		(validsalida)
);


paralelo_serial p2s(
			/*AUTOINST*/
			//ENTRADAS
			
			.clk_4f			(clk_4f),
			.clk_32f		(clk_32f),
			.in_serial		(Salida_conductual [7:0]),
			.valid_in		(validsalida),
			.reset			(reset),
			
			//SALIDAS
			.out_serial_conductual (out_serial_conductual)
			
);


serialparalelotx serialaparalelotx(
    /*AUTOINST*/
                //ENTRADAS
                .reset     (reset),
                .clk_32f    (clk_32f),
                .clk_4f    (clk_4f),
                .IDLin      (out_serial2_conductual),

                //SALIDAS
                .data_serial_paraleloTX (data_serial_paraleloRX [7:0]),
                .active_serial_paraleloTX   (active),
                .IDLEOut    (IDLEOut)
);
endmodule

phy_tx/BancoPruebas_Tx.v
// Banco de pruebas, donde se conectan los datos generados por el probador y el phy_tx


`timescale 1ms/100ps
`include "phy_tx.v"
`include "probador_Tx.v"

module BancoPruebas;

        wire reset;
		wire clk_4f;
		wire clk_32f;
        wire clk_2f;

		wire data_out;                                      //Salida al receptor
        wire data_sp;                                       //Entrada al serial paralelo
        wire active;                                       //Entrada al serial paralelo
        wire [7:0] In_0, In_1, In_2, In_3;                  //Entradas para el modulo transmisor
        wire [7:0] res_In_0, res_In_1, res_In_2, res_In_3;                  //Entradas para el modulo transmisor
        wire validIn_0, validIn_1, validIn_2, validIn_3;    //Validadores de entrada
        

        phy_tx transmisior(
 
            .reset(reset),
            .active(active),
            .clk_f(clk_f),
            .clk_2f(clk_2f),
            .clk_4f(clk_4f),
            //.clk_32f(clk_32f),

            .data_in0(In_0),
            .data_in1(In_1),
            .data_in2(In_2),
            .data_in3(In_3),

            .valid0(validIn_0),
            .valid1(validIn_1),
            .valid2(validIn_2),
            .valid3(validIn_3),

            .out_serial_conductual(data_out),
            .out_serial2_conductual(data_sp),

            .recirculador_desactivado0(res_In_0),
            .recirculador_desactivado1(res_In_1),
            .recirculador_desactivado2(res_In_2),
            .recirculador_desactivado3(res_In_3)

);


        probador_tx Probador(
            
            .reset(reset),
            .clk_f(clk_f),
            .clk_2f(clk_2f),
            .clk_4f(clk_4f),
            .active(active),
            //.clk_32f(clk_32f),

            .data_in0(In_0),
            .data_in1(In_1),
            .data_in2(In_2),
            .data_in3(In_3),

            .valid0(validIn_0),
            .valid1(validIn_1),
            .valid2(validIn_2),
            .valid3(validIn_3),

            .recirculador_desactivado0(res_In_0),
            .recirculador_desactivado1(res_In_1),
            .recirculador_desactivado2(res_In_2),
            .recirculador_desactivado3(res_In_3),

            .out_serial2_conductual(data_sp),
            .out_serial_conductual(data_out)

        );

endmodule

phy_tx/PHYTX.vcd
$date
	Tue Jun  8 17:38:19 2021
$end
$version
	Icarus Verilog
$end
$timescale
	100ps
$end
$scope module BancoPruebas $end
$var wire 1 ! active $end
$var wire 1 " validIn_3 $end
$var wire 1 # validIn_2 $end
$var wire 1 $ validIn_1 $end
$var wire 1 % validIn_0 $end
$var wire 1 & reset $end
$var wire 8 ' res_In_3 [7:0] $end
$var wire 8 ( res_In_2 [7:0] $end
$var wire 8 ) res_In_1 [7:0] $end
$var wire 8 * res_In_0 [7:0] $end
$var wire 1 + data_sp $end
$var wire 1 , data_out $end
$var wire 1 - clk_f $end
$var wire 1 . clk_4f $end
$var wire 1 / clk_2f $end
$var wire 8 0 In_3 [7:0] $end
$var wire 8 1 In_2 [7:0] $end
$var wire 8 2 In_1 [7:0] $end
$var wire 8 3 In_0 [7:0] $end
$scope module Probador $end
$var wire 8 4 recirculador_desactivado3 [7:0] $end
$var wire 8 5 recirculador_desactivado2 [7:0] $end
$var wire 8 6 recirculador_desactivado1 [7:0] $end
$var wire 8 7 recirculador_desactivado0 [7:0] $end
$var wire 1 , out_serial_conductual $end
$var reg 1 8 active $end
$var reg 1 / clk_2f $end
$var reg 1 . clk_4f $end
$var reg 1 - clk_f $end
$var reg 8 9 data_in0 [7:0] $end
$var reg 8 : data_in1 [7:0] $end
$var reg 8 ; data_in2 [7:0] $end
$var reg 8 < data_in3 [7:0] $end
$var reg 1 + out_serial2_conductual $end
$var reg 1 & reset $end
$var reg 1 % valid0 $end
$var reg 1 $ valid1 $end
$var reg 1 # valid2 $end
$var reg 1 " valid3 $end
$upscope $end
$scope module transmisior $end
$var wire 1 ! active $end
$var wire 1 / clk_2f $end
$var wire 1 = clk_32f $end
$var wire 1 . clk_4f $end
$var wire 1 - clk_f $end
$var wire 8 > data_in0 [7:0] $end
$var wire 8 ? data_in1 [7:0] $end
$var wire 8 @ data_in2 [7:0] $end
$var wire 8 A data_in3 [7:0] $end
$var wire 1 + out_serial2_conductual $end
$var wire 1 & reset $end
$var wire 1 % valid0 $end
$var wire 1 $ valid1 $end
$var wire 1 # valid2 $end
$var wire 1 " valid3 $end
$var wire 1 B validsalida $end
$var wire 1 C valid_out_recirculador3 $end
$var wire 1 D valid_out_recirculador2 $end
$var wire 1 E valid_out_recirculador1 $end
$var wire 1 F valid_out_recirculador0 $end
$var wire 8 G recirculador_desactivado3 [7:0] $end
$var wire 8 H recirculador_desactivado2 [7:0] $end
$var wire 8 I recirculador_desactivado1 [7:0] $end
$var wire 8 J recirculador_desactivado0 [7:0] $end
$var wire 1 , out_serial_conductual $end
$var wire 8 K data_serial_paraleloRX [7:0] $end
$var wire 8 L Salida_conductual [7:0] $end
$var wire 1 M IDLEOut $end
$var wire 8 N Entrada3 [7:0] $end
$var wire 8 O Entrada2 [7:0] $end
$var wire 8 P Entrada1 [7:0] $end
$var wire 8 Q Entrada0 [7:0] $end
$scope module muxess $end
$var wire 1 / clk_2f $end
$var wire 1 . clk_4f $end
$var wire 1 - clk_f $end
$var wire 1 & reset $end
$var wire 1 B validsalida $end
$var wire 1 R validsalida0 $end
$var wire 1 S validsalida1 $end
$var wire 1 C validEntrada3 $end
$var wire 1 D validEntrada2 $end
$var wire 1 E validEntrada1 $end
$var wire 1 F validEntrada0 $end
$var wire 8 T Salida_conductual [7:0] $end
$var wire 8 U Salida1 [7:0] $end
$var wire 8 V Salida0 [7:0] $end
$var wire 8 W Entrada3 [7:0] $end
$var wire 8 X Entrada2 [7:0] $end
$var wire 8 Y Entrada1 [7:0] $end
$var wire 8 Z Entrada0 [7:0] $end
$scope module muxitol2 $end
$var wire 1 . clk_4f $end
$var wire 1 & reset $end
$var wire 1 R validEntrada0 $end
$var wire 1 R validsalida $end
$var wire 1 S validEntrada1 $end
$var wire 8 [ Salida_conductual [7:0] $end
$var wire 8 \ Entrada1 [7:0] $end
$var wire 8 ] Entrada0 [7:0] $end
$scope module mux1 $end
$var wire 1 . clk $end
$var wire 1 & reset $end
$var wire 1 R validEntrada0 $end
$var wire 1 S validEntrada1 $end
$var wire 8 ^ Entrada1 [7:0] $end
$var wire 8 _ Entrada0 [7:0] $end
$var reg 8 ` Salida_conductual [7:0] $end
$var reg 1 a selector $end
$var reg 1 b validsalida $end
$upscope $end
$upscope $end
$scope module muxl1 $end
$var wire 1 / clk_2f $end
$var wire 1 & reset $end
$var wire 1 R validsalida0 $end
$var wire 1 S validsalida1 $end
$var wire 1 C validEntrada3 $end
$var wire 1 D validEntrada2 $end
$var wire 1 E validEntrada1 $end
$var wire 1 F validEntrada0 $end
$var wire 8 c Salida1 [7:0] $end
$var wire 8 d Salida0 [7:0] $end
$var wire 8 e Entrada3 [7:0] $end
$var wire 8 f Entrada2 [7:0] $end
$var wire 8 g Entrada1 [7:0] $end
$var wire 8 h Entrada0 [7:0] $end
$scope module mux1 $end
$var wire 1 / clk $end
$var wire 1 & reset $end
$var wire 1 E validEntrada1 $end
$var wire 1 F validEntrada0 $end
$var wire 8 i Entrada1 [7:0] $end
$var wire 8 j Entrada0 [7:0] $end
$var reg 8 k Salida_conductual [7:0] $end
$var reg 1 l selector $end
$var reg 1 m validsalida $end
$upscope $end
$scope module mux2 $end
$var wire 1 / clk $end
$var wire 1 & reset $end
$var wire 1 C validEntrada1 $end
$var wire 1 D validEntrada0 $end
$var wire 8 n Entrada1 [7:0] $end
$var wire 8 o Entrada0 [7:0] $end
$var reg 8 p Salida_conductual [7:0] $end
$var reg 1 q selector $end
$var reg 1 S validsalida $end
$upscope $end
$upscope $end
$upscope $end
$scope module p2s $end
$var wire 1 = clk_32f $end
$var wire 1 . clk_4f $end
$var wire 8 r in_serial [7:0] $end
$var wire 1 & reset $end
$var wire 1 B valid_in $end
$var reg 1 , out_serial_conductual $end
$var reg 3 s selector [2:0] $end
$var reg 3 t selector_2 [2:0] $end
$upscope $end
$scope module recirculadorphy $end
$var wire 1 ! active $end
$var wire 1 - clk $end
$var wire 8 u data_in0 [7:0] $end
$var wire 8 v data_in1 [7:0] $end
$var wire 8 w data_in2 [7:0] $end
$var wire 8 x data_in3 [7:0] $end
$var wire 1 & reset $end
$var wire 1 % valid0 $end
$var wire 1 $ valid1 $end
$var wire 1 # valid2 $end
$var wire 1 " valid3 $end
$var reg 8 y recirculador_activo0 [7:0] $end
$var reg 8 z recirculador_activo1 [7:0] $end
$var reg 8 { recirculador_activo2 [7:0] $end
$var reg 8 | recirculador_activo3 [7:0] $end
$var reg 8 } recirculador_desactivado0 [7:0] $end
$var reg 8 ~ recirculador_desactivado1 [7:0] $end
$var reg 8 !" recirculador_desactivado2 [7:0] $end
$var reg 8 "" recirculador_desactivado3 [7:0] $end
$var reg 1 F valid_out_recirculador0 $end
$var reg 1 E valid_out_recirculador1 $end
$var reg 1 D valid_out_recirculador2 $end
$var reg 1 C valid_out_recirculador3 $end
$upscope $end
$scope module serialaparalelotx $end
$var wire 1 + IDLin $end
$var wire 1 = clk_32f $end
$var wire 1 . clk_4f $end
$var wire 1 & reset $end
$var reg 1 M IDLEOut $end
$var reg 1 #" active_serial_paraleloTX $end
$var reg 8 $" buffer [7:0] $end
$var reg 8 %" buffer_pasado [7:0] $end
$var reg 8 &" data_serial_paraleloTX [7:0] $end
$var integer 32 '" contador [31:0] $end
$var integer 32 (" contador_BC [31:0] $end
$upscope $end
$upscope $end
$upscope $end
$enddefinitions $end
#0
$dumpvars
bx ("
bx '"
bx &"
bx %"
bx $"
x#"
b0 ""
b0 !"
b0 ~
b0 }
b0 |
b0 {
b0 z
b0 y
b10010 x
b10101010 w
b11111101 v
b0 u
bx t
bx s
b0 r
0q
b0 p
b0 o
b0 n
xm
0l
b0 k
b0 j
b0 i
b0 h
b0 g
b0 f
b0 e
b0 d
b0 c
xb
0a
b0 `
b0 _
b0 ^
b0 ]
b0 \
b0 [
b0 Z
b0 Y
b0 X
b0 W
b0 V
b0 U
b0 T
xS
xR
b0 Q
b0 P
b0 O
b0 N
xM
b0 L
bx K
b0 J
b0 I
b0 H
b0 G
0F
0E
0D
0C
zB
b10010 A
b10101010 @
b11111101 ?
b0 >
z=
b10010 <
b10101010 ;
b11111101 :
b0 9
18
b0 7
b0 6
b0 5
b0 4
b0 3
b11111101 2
b10101010 1
b10010 0
1/
1.
1-
x,
0+
b0 *
b0 )
b0 (
b0 '
0&
1%
1$
1#
1"
x!
$end
#80000000
0.
#160000000
1.
0/
#240000000
0.
0-
#320000000
1.
1/
#400000000
0.
#480000000
1.
0/
1-
#560000000
0.
#640000000
1.
1/
#720000000
0.
0-
#800000000
1.
0/
#880000000
0.
#960000000
1.
1/
1-
#1040000000
0.
#1120000000
1.
0/
#1200000000
0.
0-
#1280000000
1.
1/
#1360000000
0.
#1440000000
b10001 0
b10001 <
b10001 A
b10001 x
b11110000 2
b11110000 :
b11110000 ?
b11110000 v
1.
0/
1-
#1520000000
0.
#1600000000
1.
1/
#1680000000
0.
0-
#1760000000
1.
0/
#1840000000
0.
#1920000000
1.
1/
1-
#2000000000
0.
#2080000000
1.
0/
#2160000000
0.
0-
#2240000000
1.
1/
#2320000000
0.
#2400000000
b10010 0
b10010 <
b10010 A
b10010 x
b11110010 2
b11110010 :
b11110010 ?
b11110010 v
1&
1.
0/
1-
#2480000000
0.
#2560000000
1a
0R
0b
1l
0m
1q
0S
1.
1/
#2640000000
0.
0-
#2720000000
0a
1.
0/
#2800000000
0.
#2880000000
1a
0q
0l
1C
1D
1E
1F
1.
1/
1-
#2960000000
0.
#3040000000
0a
1.
0/
#3120000000
0.
0-
#3200000000
1a
1l
xR
1m
1q
1S
1.
1/
#3280000000
0.
#3360000000
1R
1b
0a
b10111010 1
b10111010 ;
b10111010 @
b10111010 w
b11110010 2
b11110010 :
b11110010 ?
b11110010 v
1.
0/
1-
#3440000000
0.
#3520000000
1a
0q
0l
1.
1/
#3600000000
0.
0-
#3680000000
0a
1.
0/
#3760000000
0.
#3840000000
1a
1l
1q
1.
1/
1-
#3920000000
0.
#4000000000
0a
1.
0/
#4080000000
0.
0-
#4160000000
1a
0q
0l
1.
1/
#4240000000
0.
